playwrightauthor/__init__.py
playwrightauthor/__main__.py
playwrightauthor/author.py
playwrightauthor/browser_manager.py
playwrightauthor/cli.py
playwrightauthor/config.py
playwrightauthor/connection.py
playwrightauthor/exceptions.py
playwrightauthor/lazy_imports.py
playwrightauthor/monitoring.py
playwrightauthor/onboarding.py
playwrightauthor/state_manager.py
playwrightauthor/typing.py
playwrightauthor/browser/__init__.py
playwrightauthor/browser/finder.py
playwrightauthor/browser/installer.py
playwrightauthor/browser/launcher.py
playwrightauthor/browser/process.py
playwrightauthor/repl/__init__.py
playwrightauthor/repl/completion.py
playwrightauthor/repl/engine.py
playwrightauthor/templates/onboarding.html
playwrightauthor/utils/logger.py
playwrightauthor/utils/paths.py
playwrightauthor-1.0.13.dist-info/METADATA
playwrightauthor-1.0.13.dist-info/WHEEL
playwrightauthor-1.0.13.dist-info/entry_points.txt
playwrightauthor-1.0.13.dist-info/licenses/LICENSE
playwrightauthor-1.0.13.dist-info/RECORD
