Metadata-Version: 2.4
Name: playwrightauthor
Version: 1.0.13
Summary: Your personal, authenticated browser for Playwright, ready in one line of code.
Project-URL: Homepage, https://github.com/twardoch/playwrightauthor
Project-URL: Bug Tracker, https://github.com/twardoch/playwrightauthor/issues
Author-email: Adam Twardoch <adam+github@twardoch.com>
License-File: LICENSE
Classifier: License :: OSI Approved :: MIT License
Classifier: Operating System :: OS Independent
Classifier: Programming Language :: Python :: 3
Requires-Python: >=3.12
Requires-Dist: fire
Requires-Dist: loguru
Requires-Dist: platformdirs
Requires-Dist: playwright
Requires-Dist: prompt-toolkit>=3.0.0
Requires-Dist: psutil
Requires-Dist: requests
Requires-Dist: rich
